sichuanMojo/__init__.py
sichuanMojo/tidy_pd.py
sichuanMojo-0.1.2.dist-info/LICENSE
sichuanMojo-0.1.2.dist-info/METADATA
sichuanMojo-0.1.2.dist-info/WHEEL
sichuanMojo-0.1.2.dist-info/top_level.txt
sichuanMojo-0.1.2.dist-info/RECORD
