Metadata-Version: 2.1
Name: sichuanMojo
Version: 0.1.2
Summary: A series of utility functions to help with tidy dataframe.
Home-page: https://github.com/jienagu/sichuanMojo
Author: Jiena Gu McLellan
Author-email: jienagu90@gmail.com
License: Apache License 2.0
License-File: LICENSE
Requires-Dist: pandas
